setup.py
slackmail/__init__.py
slackmail/db_server.py
slackmail/simple_server.py
slackmail/smtp_util.py
slackmail/test_send.py
slackmail.egg-info/PKG-INFO
slackmail.egg-info/SOURCES.txt
slackmail.egg-info/dependency_links.txt
slackmail.egg-info/entry_points.txt
slackmail.egg-info/not-zip-safe
slackmail.egg-info/pbr.json
slackmail.egg-info/requires.txt
slackmail.egg-info/top_level.txt