Metadata-Version: 1.0
Name: slackmail
Version: 0.1
Summary: Email-to-slack bridge.
Home-page: http://github.com/iodine/slackmail
Author: UNKNOWN
Author-email: UNKNOWN
License: UNKNOWN
Platform: UNKNOWN
